LICENSE.md
MANIFEST.in
README.md
setup.py
admin_black/__init__.py
admin_black/apps.py
admin_black/forms.py
admin_black/urls.py
admin_black/utils.py
admin_black/views.py
admin_black/migrations/0001_initial.py
admin_black/migrations/__init__.py
admin_black/static/.gitkeep
admin_black/static/assets/css/black-dashboard.css
admin_black/static/assets/css/black-dashboard.css.map
admin_black/static/assets/css/black-dashboard.min.css
admin_black/static/assets/css/forms.css
admin_black/static/assets/css/nucleo-icons.css
admin_black/static/assets/css/theme-switcher.css
admin_black/static/assets/css/widgets.css
admin_black/static/assets/demo/demo.css
admin_black/static/assets/demo/demo.js
admin_black/static/assets/fonts/nucleo.eot
admin_black/static/assets/fonts/nucleo.ttf
admin_black/static/assets/fonts/nucleo.woff
admin_black/static/assets/fonts/nucleo.woff2
admin_black/static/assets/img/12345.png
admin_black/static/assets/img/anime3.png
admin_black/static/assets/img/anime6.png
admin_black/static/assets/img/apple-icon.png
admin_black/static/assets/img/bg5.jpg
admin_black/static/assets/img/default-avatar.png
admin_black/static/assets/img/emilyz.jpg
admin_black/static/assets/img/favicon.png
admin_black/static/assets/img/header.jpg
admin_black/static/assets/img/icon-addlink.svg
admin_black/static/assets/img/icon-calendar.svg
admin_black/static/assets/img/icon-clock.svg
admin_black/static/assets/img/icon-unknown-alt.svg
admin_black/static/assets/img/icon-unknown.svg
admin_black/static/assets/img/img_3115.jpg
admin_black/static/assets/img/james.jpg
admin_black/static/assets/img/mike.jpg
admin_black/static/assets/img/now-logo.png
admin_black/static/assets/img/search.svg
admin_black/static/assets/img/selector-icons.svg
admin_black/static/assets/img/icons/add.svg
admin_black/static/assets/js/black-dashboard.js
admin_black/static/assets/js/black-dashboard.js.map
admin_black/static/assets/js/black-dashboard.min.js
admin_black/static/assets/js/themeSettings.js
django_admin_black.egg-info/PKG-INFO
django_admin_black.egg-info/SOURCES.txt
django_admin_black.egg-info/dependency_links.txt
django_admin_black.egg-info/not-zip-safe
django_admin_black.egg-info/top_level.txt
